fences/__init__.py
fences/core/__init__.py
fences/core/debug.py
fences/core/exception.py
fences/core/node.py
fences/core/random.py
fences/core/render.py
fences/core/util.py
fences/grammar/__ini__.py
fences/grammar/convert.py
fences/grammar/exceptions.py
fences/grammar/types.py
fences/json_schema/__init__.py
fences/json_schema/config.py
fences/json_schema/exceptions.py
fences/json_schema/json_pointer.py
fences/json_schema/normalize.py
fences/json_schema/parse.py
fences/open_api/__init__.py
fences/open_api/exceptions.py
fences/open_api/format.py
fences/open_api/generate.py
fences/open_api/open_api.py
fences/open_api/resolver.py
fences/regex/__init__.py
fences/regex/exception.py
fences/regex/grammar.py
fences/regex/parse.py
fences/xml_schema/__init__.py
fences/xml_schema/config.py
fences/xml_schema/exception.py
fences/xml_schema/parse.py
fences/xml_schema/xpath.py
fences-1.4.0.dist-info/LICENSE
fences-1.4.0.dist-info/METADATA
fences-1.4.0.dist-info/WHEEL
fences-1.4.0.dist-info/top_level.txt
fences-1.4.0.dist-info/RECORD
