Metadata-Version: 2.1
Name: fences
Version: 1.4.0
Summary: Generate samples for various schemas like json schema, xml schema and regex
License: MIT License
Project-URL: Homepage, https://github.com/ifak/fences
Keywords: xml,json,regex,schema
Classifier: License :: OSI Approved :: MIT License
Classifier: Programming Language :: Python
Classifier: Programming Language :: Python :: 3
Requires-Python: >=3.6
License-File: LICENSE
Requires-Dist: typing-extensions>=4
